AUTHORS.rst
CONTRIBUTING.rst
HISTORY.rst
LICENSE
MANIFEST.in
README.md
classifiers
requirements.txt
setup.cfg
setup.py
threebot_stats/__init__.py
threebot_stats/admin.py
threebot_stats/models.py
threebot_stats/urls.py
threebot_stats/utils.py
threebot_stats/views.py
threebot_stats.egg-info/PKG-INFO
threebot_stats.egg-info/SOURCES.txt
threebot_stats.egg-info/dependency_links.txt
threebot_stats.egg-info/not-zip-safe
threebot_stats.egg-info/requires.txt
threebot_stats.egg-info/top_level.txt
threebot_stats/management/__init__.py
threebot_stats/management/commands/__init__.py
threebot_stats/static/css/threebot_stats.css
threebot_stats/static/img/.gitignore
threebot_stats/static/js/threebot_stats.js
threebot_stats/templates/threebot_stats/base.html
threebot_stats/templates/threebot_stats/workflow_stats.html
threebot_stats/templatetags/__init__.py
threebot_stats/templatetags/threebot_stats_tags.py