Metadata-Version: 1.1
Name: threebot-stats
Version: 0.1.1
Summary: Your project description goes here
Home-page: https://github.com/arteria/3bot-stats
Author: arteria GmbH
Author-email: admin@arteria.ch
License: BSD
Keywords: 3bot-stats
Platform: UNKNOWN
Classifier: Development Status :: 2 - Pre-Alpha
Classifier: Framework :: Django
Classifier: Intended Audience :: Developers
Classifier: License :: OSI Approved :: BSD License
Classifier: Natural Language :: English
Classifier: Programming Language :: Python :: 2
Classifier: Programming Language :: Python :: 3
